certpatrol.py
certpatrol-0.1.2.dist-info/licenses/LICENSE
certpatrol-0.1.2.dist-info/METADATA
certpatrol-0.1.2.dist-info/WHEEL
certpatrol-0.1.2.dist-info/entry_points.txt
certpatrol-0.1.2.dist-info/top_level.txt
certpatrol-0.1.2.dist-info/RECORD
