Metadata-Version: 2.4
Name: certpatrol
Version: 0.1.2
Summary: A fast, lightweight Certificate Transparency (CT) log tailer for your terminal. Filter domains with regex, run locally for privacy, and monitor in real time—no third-party servers, no tracking. A modern, local, privacy-friendly CertStream alternative.
Author: Martin Aberastegue
License: MIT License
Project-URL: Homepage, https://github.com/toritoio/certpatrol
Project-URL: Repository, https://github.com/toritoio/certpatrol
Project-URL: Issues, https://github.com/toritoio/certpatrol/issues
Requires-Python: >=3.6
License-File: LICENSE
Requires-Dist: requests
Requires-Dist: cryptography
Requires-Dist: idna
Requires-Dist: tldextract
Requires-Dist: psutil
Dynamic: license-file
